build/lib/build/lib/deep_utils/deduplication/__init__.py
build/lib/build/lib/deep_utils/deduplication/elasticsearch.py
build/lib/build/lib/deep_utils/deduplication/tests.py
build/lib/build/lib/deep_utils/deduplication/utils.py
build/lib/build/lib/deep_utils/deduplication/vector_generator.py
build/lib/build/lib/deep_utils/deduplication/scripts/process_raw_trigrams.py
build/lib/build/lib/deep_utils/deduplication/scripts/raw_trigrams.py
build/lib/build/lib/deep_utils/deduplication/trigrams/__init__.py
build/lib/build/lib/deep_utils/deduplication/trigrams/en.py
build/lib/build/lib/deep_utils/deduplication/trigrams/es.py
build/lib/build/lib/deep_utils/deduplication/trigrams/fr.py
build/lib/deep_utils/deduplication/__init__.py
build/lib/deep_utils/deduplication/elasticsearch.py
build/lib/deep_utils/deduplication/tests.py
build/lib/deep_utils/deduplication/utils.py
build/lib/deep_utils/deduplication/vector_generator.py
build/lib/deep_utils/deduplication/scripts/process_raw_trigrams.py
build/lib/deep_utils/deduplication/scripts/raw_trigrams.py
build/lib/deep_utils/deduplication/trigrams/__init__.py
build/lib/deep_utils/deduplication/trigrams/en.py
build/lib/deep_utils/deduplication/trigrams/es.py
build/lib/deep_utils/deduplication/trigrams/fr.py
deep_utils/deduplication/__init__.py
deep_utils/deduplication/elasticsearch.py
deep_utils/deduplication/tests.py
deep_utils/deduplication/utils.py
deep_utils/deduplication/vector_generator.py
deep_utils/deduplication/scripts/process_raw_trigrams.py
deep_utils/deduplication/scripts/raw_trigrams.py
deep_utils/deduplication/trigrams/__init__.py
deep_utils/deduplication/trigrams/en.py
deep_utils/deduplication/trigrams/es.py
deep_utils/deduplication/trigrams/fr.py
deep_utils.deduplication-1.0.8.dist-info/METADATA
deep_utils.deduplication-1.0.8.dist-info/WHEEL
deep_utils.deduplication-1.0.8.dist-info/top_level.txt
deep_utils.deduplication-1.0.8.dist-info/RECORD
