Metadata-Version: 2.1
Name: deep-utils.deduplication
Version: 1.0.8
Summary: Document deduplication package for DEEP
Home-page: https://github.com/the-deep/deep-server-utils
Author: Bibek Pandey
Author-email: bibek.pandey@togglecorp.com
License: MIT
Platform: UNKNOWN
Classifier: License :: OSI Approved :: MIT License
Classifier: Programming Language :: Python :: 3
Classifier: Topic :: Text Processing :: General
Classifier: Topic :: Utilities
Classifier: Operating System :: OS Independent
Requires-Dist: boto3 (==1.9.88)
Requires-Dist: elasticsearch (==7.8.1)
Requires-Dist: requests-aws4auth (==1.0)
